twistedgit
