Metadata-Version: 1.0
Name: TwistedGit
Version: 0.2.1
Summary: Twisted-based implementation of the network protocols supported by git (git://, ssh:// and http://)
Home-page: https://github.com/mensi/twistedgit
Author: Manuel Stocker
Author-email: mensi@mensi.ch
License: GPL
Keywords: git ssh http
Platform: UNKNOWN
